{
  "data": {
    "id": "ember-6.8.1-AssertAgainstAttrs",
    "type": "class",
    "attributes": {
      "name": "AssertAgainstAttrs",
      "shortname": "AssertAgainstAttrs",
      "classitems": [],
      "plugins": [],
      "extensions": [],
      "plugin_for": [],
      "extension_for": [],
      "module": "ember",
      "namespace": "",
      "file": "packages/@ember/template-compiler/lib/plugins/assert-against-attrs.ts",
      "line": 11,
      "description": "A Glimmer2 AST transformation that asserts against\n\n```handlebars\n{{attrs.foo.bar}}\n```\n\n...as well as `{{#if attrs.foo}}`, `{{deeply (nested attrs.foobar.baz)}}`.",
      "access": "private",
      "tagname": "",
      "methods": [],
      "events": [],
      "properties": []
    },
    "relationships": {
      "parent-class": {
        "data": null
      },
      "descendants": {
        "data": []
      },
      "module": {
        "data": {
          "id": "ember-6.8.1-ember",
          "type": "module"
        }
      },
      "project-version": {
        "data": {
          "id": "ember-6.8.1",
          "type": "project-version"
        }
      }
    }
  }
}