{"data":{"id":"ember-3.2.1","type":"project-version","attributes":{"version":"3.2.1"},"relationships":{"classes":{"data":[{"id":"ember-3.2.1-RSVP.EventTarget","type":"class"},{"id":"ember-3.2.1-RSVP.Promise","type":"class"},{"id":"ember-3.2.1-Container","type":"class"},{"id":"ember-3.2.1-Registry","type":"class"},{"id":"ember-3.2.1-ApplicationInstance","type":"class"},{"id":"ember-3.2.1-ApplicationInstance.BootOptions","type":"class"},{"id":"ember-3.2.1-Application","type":"class"},{"id":"ember-3.2.1-EngineInstance","type":"class"},{"id":"ember-3.2.1-Engine","type":"class"},{"id":"ember-3.2.1-GlobalsResolver","type":"class"},{"id":"ember-3.2.1-EmberError","type":"class"},{"id":"ember-3.2.1-ContainerDebugAdapter","type":"class"},{"id":"ember-3.2.1-DataAdapter","type":"class"},{"id":"ember-3.2.1-Checkbox","type":"class"},{"id":"ember-3.2.1-LinkComponent","type":"class"},{"id":"ember-3.2.1-TextArea","type":"class"},{"id":"ember-3.2.1-TextField","type":"class"},{"id":"ember-3.2.1-ComponentStateBucket","type":"class"},{"id":"ember-3.2.1-Component","type":"class"},{"id":"ember-3.2.1-Helper","type":"class"},{"id":"ember-3.2.1-ComputedProperty","type":"class"},{"id":"ember-3.2.1-Descriptor","type":"class"},{"id":"ember-3.2.1-Ember.InjectedProperty","type":"class"},{"id":"ember-3.2.1-Libraries","type":"class"},{"id":"ember-3.2.1-Ember.OrderedSet","type":"class"},{"id":"ember-3.2.1-Ember.Map","type":"class"},{"id":"ember-3.2.1-Ember.MapWithDefault","type":"class"},{"id":"ember-3.2.1-Mixin","type":"class"},{"id":"ember-3.2.1-ObserverSet","type":"class"},{"id":"ember-3.2.1-Ember.ControllerMixin","type":"class"},{"id":"ember-3.2.1-Location","type":"class"},{"id":"ember-3.2.1-HashLocation","type":"class"},{"id":"ember-3.2.1-HistoryLocation","type":"class"},{"id":"ember-3.2.1-NoneLocation","type":"class"},{"id":"ember-3.2.1-RouterService","type":"class"},{"id":"ember-3.2.1-RoutingService","type":"class"},{"id":"ember-3.2.1-BucketCache","type":"class"},{"id":"ember-3.2.1-Route","type":"class"},{"id":"ember-3.2.1-EmberRouter","type":"class"},{"id":"ember-3.2.1-Controller","type":"class"},{"id":"ember-3.2.1-Ember.ProxyMixin","type":"class"},{"id":"ember-3.2.1-Ember.ActionHandler","type":"class"},{"id":"ember-3.2.1-EmberArray","type":"class"},{"id":"ember-3.2.1-MutableArray","type":"class"},{"id":"ember-3.2.1-Ember.NativeArray","type":"class"},{"id":"ember-3.2.1-Ember.Comparable","type":"class"},{"id":"ember-3.2.1-ContainerProxyMixin","type":"class"},{"id":"ember-3.2.1-Ember.Copyable","type":"class"},{"id":"ember-3.2.1-Ember.Enumerable","type":"class"},{"id":"ember-3.2.1-Evented","type":"class"},{"id":"ember-3.2.1-Ember.MutableEnumerable","type":"class"},{"id":"ember-3.2.1-Observable","type":"class"},{"id":"ember-3.2.1-PromiseProxyMixin","type":"class"},{"id":"ember-3.2.1-RegistryProxyMixin","type":"class"},{"id":"ember-3.2.1-Ember.TargetActionSupport","type":"class"},{"id":"ember-3.2.1-ArrayProxy","type":"class"},{"id":"ember-3.2.1-CoreObject","type":"class"},{"id":"ember-3.2.1-Ember.Namespace","type":"class"},{"id":"ember-3.2.1-EmberObject","type":"class"},{"id":"ember-3.2.1-ObjectProxy","type":"class"},{"id":"ember-3.2.1-Service","type":"class"},{"id":"ember-3.2.1-String","type":"class"},{"id":"ember-3.2.1-TestAdapter","type":"class"},{"id":"ember-3.2.1-Ember.Test.QUnitAdapter","type":"class"},{"id":"ember-3.2.1-Ember.Test","type":"class"},{"id":"ember-3.2.1-Ember.ActionSupport","type":"class"},{"id":"ember-3.2.1-Ember.ClassNamesSupport","type":"class"},{"id":"ember-3.2.1-Ember.TextSupport","type":"class"},{"id":"ember-3.2.1-Ember.ViewMixin","type":"class"},{"id":"ember-3.2.1-Ember.EventDispatcher","type":"class"},{"id":"ember-3.2.1-Ember.CoreView","type":"class"}]},"namespaces":{"data":[{"id":"ember-3.2.1-Ember.FEATURES","type":"namespace"},{"id":"ember-3.2.1-Instrumentation","type":"namespace"},{"id":"ember-3.2.1-AutoLocation","type":"namespace"},{"id":"ember-3.2.1-Ember.inject","type":"namespace"}]},"modules":{"data":[{"id":"ember-3.2.1-@ember/application","type":"module"},{"id":"ember-3.2.1-@ember/engine","type":"module"},{"id":"ember-3.2.1-@ember/debug","type":"module"},{"id":"ember-3.2.1-@ember/error","type":"module"},{"id":"ember-3.2.1-ember","type":"module"},{"id":"ember-3.2.1-@ember/component","type":"module"},{"id":"ember-3.2.1-@ember/routing","type":"module"},{"id":"ember-3.2.1-@ember/string","type":"module"},{"id":"ember-3.2.1-@ember/object","type":"module"},{"id":"ember-3.2.1-@ember/instrumentation","type":"module"},{"id":"ember-3.2.1-@ember/utils","type":"module"},{"id":"ember-3.2.1-@ember/map","type":"module"},{"id":"ember-3.2.1-@ember/polyfills","type":"module"},{"id":"ember-3.2.1-@ember/runloop","type":"module"},{"id":"ember-3.2.1-@ember/controller","type":"module"},{"id":"ember-3.2.1-@ember/array","type":"module"},{"id":"ember-3.2.1-@ember/service","type":"module"},{"id":"ember-3.2.1-@ember/test","type":"module"}]},"project":{"data":{"id":"ember","type":"project"}},"private-classes":{"data":[{"id":"ember-3.2.1-Container","type":"class"},{"id":"ember-3.2.1-Registry","type":"class"},{"id":"ember-3.2.1-ComponentStateBucket","type":"class"},{"id":"ember-3.2.1-Descriptor","type":"class"},{"id":"ember-3.2.1-Ember.InjectedProperty","type":"class"},{"id":"ember-3.2.1-Libraries","type":"class"},{"id":"ember-3.2.1-Ember.OrderedSet","type":"class"},{"id":"ember-3.2.1-Ember.Map","type":"class"},{"id":"ember-3.2.1-Ember.MapWithDefault","type":"class"},{"id":"ember-3.2.1-ObserverSet","type":"class"},{"id":"ember-3.2.1-Ember.ControllerMixin","type":"class"},{"id":"ember-3.2.1-Location","type":"class"},{"id":"ember-3.2.1-RoutingService","type":"class"},{"id":"ember-3.2.1-BucketCache","type":"class"},{"id":"ember-3.2.1-Ember.ProxyMixin","type":"class"},{"id":"ember-3.2.1-Ember.ActionHandler","type":"class"},{"id":"ember-3.2.1-Ember.Comparable","type":"class"},{"id":"ember-3.2.1-ContainerProxyMixin","type":"class"},{"id":"ember-3.2.1-Ember.Copyable","type":"class"},{"id":"ember-3.2.1-Ember.Enumerable","type":"class"},{"id":"ember-3.2.1-Ember.MutableEnumerable","type":"class"},{"id":"ember-3.2.1-RegistryProxyMixin","type":"class"},{"id":"ember-3.2.1-Ember.TargetActionSupport","type":"class"},{"id":"ember-3.2.1-Ember.ActionSupport","type":"class"},{"id":"ember-3.2.1-Ember.ClassNamesSupport","type":"class"},{"id":"ember-3.2.1-Ember.TextSupport","type":"class"},{"id":"ember-3.2.1-Ember.ViewMixin","type":"class"},{"id":"ember-3.2.1-Ember.EventDispatcher","type":"class"},{"id":"ember-3.2.1-Ember.CoreView","type":"class"}]},"public-classes":{"data":[{"id":"ember-3.2.1-RSVP.EventTarget","type":"class"},{"id":"ember-3.2.1-RSVP.Promise","type":"class"},{"id":"ember-3.2.1-ApplicationInstance","type":"class"},{"id":"ember-3.2.1-ApplicationInstance.BootOptions","type":"class"},{"id":"ember-3.2.1-Application","type":"class"},{"id":"ember-3.2.1-EngineInstance","type":"class"},{"id":"ember-3.2.1-Engine","type":"class"},{"id":"ember-3.2.1-GlobalsResolver","type":"class"},{"id":"ember-3.2.1-EmberError","type":"class"},{"id":"ember-3.2.1-ContainerDebugAdapter","type":"class"},{"id":"ember-3.2.1-DataAdapter","type":"class"},{"id":"ember-3.2.1-Checkbox","type":"class"},{"id":"ember-3.2.1-LinkComponent","type":"class"},{"id":"ember-3.2.1-TextArea","type":"class"},{"id":"ember-3.2.1-TextField","type":"class"},{"id":"ember-3.2.1-Component","type":"class"},{"id":"ember-3.2.1-Helper","type":"class"},{"id":"ember-3.2.1-ComputedProperty","type":"class"},{"id":"ember-3.2.1-Mixin","type":"class"},{"id":"ember-3.2.1-HashLocation","type":"class"},{"id":"ember-3.2.1-HistoryLocation","type":"class"},{"id":"ember-3.2.1-NoneLocation","type":"class"},{"id":"ember-3.2.1-RouterService","type":"class"},{"id":"ember-3.2.1-Route","type":"class"},{"id":"ember-3.2.1-EmberRouter","type":"class"},{"id":"ember-3.2.1-Controller","type":"class"},{"id":"ember-3.2.1-EmberArray","type":"class"},{"id":"ember-3.2.1-MutableArray","type":"class"},{"id":"ember-3.2.1-Ember.NativeArray","type":"class"},{"id":"ember-3.2.1-Evented","type":"class"},{"id":"ember-3.2.1-Observable","type":"class"},{"id":"ember-3.2.1-PromiseProxyMixin","type":"class"},{"id":"ember-3.2.1-ArrayProxy","type":"class"},{"id":"ember-3.2.1-CoreObject","type":"class"},{"id":"ember-3.2.1-Ember.Namespace","type":"class"},{"id":"ember-3.2.1-EmberObject","type":"class"},{"id":"ember-3.2.1-ObjectProxy","type":"class"},{"id":"ember-3.2.1-Service","type":"class"},{"id":"ember-3.2.1-String","type":"class"},{"id":"ember-3.2.1-TestAdapter","type":"class"},{"id":"ember-3.2.1-Ember.Test.QUnitAdapter","type":"class"},{"id":"ember-3.2.1-Ember.Test","type":"class"}]},"private-namespaces":{"data":[{"id":"ember-3.2.1-Instrumentation","type":"namespace"}]},"public-namespaces":{"data":[{"id":"ember-3.2.1-Ember.FEATURES","type":"namespace"},{"id":"ember-3.2.1-AutoLocation","type":"namespace"},{"id":"ember-3.2.1-Ember.inject","type":"namespace"}]},"private-modules":{"data":[{"id":"ember-3.2.1-ember","type":"module"},{"id":"ember-3.2.1-@ember/instrumentation","type":"module"},{"id":"ember-3.2.1-@ember/map","type":"module"}]},"public-modules":{"data":[{"id":"ember-3.2.1-@ember/application","type":"module"},{"id":"ember-3.2.1-@ember/engine","type":"module"},{"id":"ember-3.2.1-@ember/debug","type":"module"},{"id":"ember-3.2.1-@ember/error","type":"module"},{"id":"ember-3.2.1-@ember/component","type":"module"},{"id":"ember-3.2.1-@ember/routing","type":"module"},{"id":"ember-3.2.1-@ember/string","type":"module"},{"id":"ember-3.2.1-@ember/object","type":"module"},{"id":"ember-3.2.1-@ember/utils","type":"module"},{"id":"ember-3.2.1-@ember/polyfills","type":"module"},{"id":"ember-3.2.1-@ember/runloop","type":"module"},{"id":"ember-3.2.1-@ember/controller","type":"module"},{"id":"ember-3.2.1-@ember/array","type":"module"},{"id":"ember-3.2.1-@ember/service","type":"module"},{"id":"ember-3.2.1-@ember/test","type":"module"}]}}},"meta":{"class":{"ember-3.2.1-RSVP.EventTarget":"ember-3.2.1-RSVP.EventTarget-cd91cf68db","ember-3.2.1-RSVP.Promise":"ember-3.2.1-RSVP.Promise-2f6fdf1f54","ember-3.2.1-Container":"ember-3.2.1-Container-c49574b981","ember-3.2.1-Registry":"ember-3.2.1-Registry-070e26c546","ember-3.2.1-ApplicationInstance":"ember-3.2.1-ApplicationInstance-9a4df8af2f","ember-3.2.1-ApplicationInstance.BootOptions":"ember-3.2.1-ApplicationInstance.BootOptions-3e2369bb55","ember-3.2.1-Application":"ember-3.2.1-Application-9af2495497","ember-3.2.1-EngineInstance":"ember-3.2.1-EngineInstance-ffd13fad22","ember-3.2.1-Engine":"ember-3.2.1-Engine-02f1e4baab","ember-3.2.1-GlobalsResolver":"ember-3.2.1-GlobalsResolver-8d77e7d5a6","ember-3.2.1-EmberError":"ember-3.2.1-EmberError-3fa2487257","ember-3.2.1-ContainerDebugAdapter":"ember-3.2.1-ContainerDebugAdapter-0722c4dc07","ember-3.2.1-DataAdapter":"ember-3.2.1-DataAdapter-c044e2b096","ember-3.2.1-Checkbox":"ember-3.2.1-Checkbox-6fde0fe376","ember-3.2.1-LinkComponent":"ember-3.2.1-LinkComponent-7cfcea3165","ember-3.2.1-TextArea":"ember-3.2.1-TextArea-b24e99cdd1","ember-3.2.1-TextField":"ember-3.2.1-TextField-95e4c4ae16","ember-3.2.1-ComponentStateBucket":"ember-3.2.1-ComponentStateBucket-a662b2f30e","ember-3.2.1-Component":"ember-3.2.1-Component-9693bf5953","ember-3.2.1-Helper":"ember-3.2.1-Helper-67c296dd3e","ember-3.2.1-ComputedProperty":"ember-3.2.1-ComputedProperty-0181488fe2","ember-3.2.1-Descriptor":"ember-3.2.1-Descriptor-508a8925be","ember-3.2.1-Ember.InjectedProperty":"ember-3.2.1-Ember.InjectedProperty-28413cc3a6","ember-3.2.1-Libraries":"ember-3.2.1-Libraries-1c19aea80a","ember-3.2.1-Ember.OrderedSet":"ember-3.2.1-Ember.OrderedSet-0a2b30ad7f","ember-3.2.1-Ember.Map":"ember-3.2.1-Ember.Map-1ce53c5641","ember-3.2.1-Ember.MapWithDefault":"ember-3.2.1-Ember.MapWithDefault-6b45db8117","ember-3.2.1-Mixin":"ember-3.2.1-Mixin-a41fe5da0c","ember-3.2.1-ObserverSet":"ember-3.2.1-ObserverSet-a3ce00e065","ember-3.2.1-Ember.ControllerMixin":"ember-3.2.1-Ember.ControllerMixin-6b023e9df5","ember-3.2.1-Location":"ember-3.2.1-Location-cc43574dd3","ember-3.2.1-HashLocation":"ember-3.2.1-HashLocation-7c5e509ddc","ember-3.2.1-HistoryLocation":"ember-3.2.1-HistoryLocation-df932f6a4e","ember-3.2.1-NoneLocation":"ember-3.2.1-NoneLocation-6f916064d4","ember-3.2.1-RouterService":"ember-3.2.1-RouterService-c05eebf3b0","ember-3.2.1-RoutingService":"ember-3.2.1-RoutingService-9af0f5a2eb","ember-3.2.1-BucketCache":"ember-3.2.1-BucketCache-fe85f41bbb","ember-3.2.1-Route":"ember-3.2.1-Route-b8ae6d583d","ember-3.2.1-EmberRouter":"ember-3.2.1-EmberRouter-01f1b48a9e","ember-3.2.1-Controller":"ember-3.2.1-Controller-5824870f0c","ember-3.2.1-Ember.ProxyMixin":"ember-3.2.1-Ember.ProxyMixin-5b13e2fa4c","ember-3.2.1-Ember.ActionHandler":"ember-3.2.1-Ember.ActionHandler-71508cb9d4","ember-3.2.1-EmberArray":"ember-3.2.1-EmberArray-a11af6c9d6","ember-3.2.1-MutableArray":"ember-3.2.1-MutableArray-df21ec5932","ember-3.2.1-Ember.NativeArray":"ember-3.2.1-Ember.NativeArray-148ccd1655","ember-3.2.1-Ember.Comparable":"ember-3.2.1-Ember.Comparable-3760fb51fa","ember-3.2.1-ContainerProxyMixin":"ember-3.2.1-ContainerProxyMixin-b06002994d","ember-3.2.1-Ember.Copyable":"ember-3.2.1-Ember.Copyable-4cd406d94d","ember-3.2.1-Ember.Enumerable":"ember-3.2.1-Ember.Enumerable-1cfe3ed9fc","ember-3.2.1-Evented":"ember-3.2.1-Evented-a93e2dc087","ember-3.2.1-Ember.MutableEnumerable":"ember-3.2.1-Ember.MutableEnumerable-3ef54eb47f","ember-3.2.1-Observable":"ember-3.2.1-Observable-8f4753250c","ember-3.2.1-PromiseProxyMixin":"ember-3.2.1-PromiseProxyMixin-0bb0f16dd1","ember-3.2.1-RegistryProxyMixin":"ember-3.2.1-RegistryProxyMixin-3f4bc5c47e","ember-3.2.1-Ember.TargetActionSupport":"ember-3.2.1-Ember.TargetActionSupport-b40a85ce9e","ember-3.2.1-ArrayProxy":"ember-3.2.1-ArrayProxy-beea169450","ember-3.2.1-CoreObject":"ember-3.2.1-CoreObject-8bb08c1f50","ember-3.2.1-Ember.Namespace":"ember-3.2.1-Ember.Namespace-6daa63e495","ember-3.2.1-EmberObject":"ember-3.2.1-EmberObject-0b14cd9fe2","ember-3.2.1-ObjectProxy":"ember-3.2.1-ObjectProxy-f6c1c3e4ed","ember-3.2.1-Service":"ember-3.2.1-Service-d2273429c9","ember-3.2.1-String":"ember-3.2.1-String-0c802f7ed9","ember-3.2.1-TestAdapter":"ember-3.2.1-TestAdapter-e4c5c10b4d","ember-3.2.1-Ember.Test.QUnitAdapter":"ember-3.2.1-Ember.Test.QUnitAdapter-a62b554b92","ember-3.2.1-Ember.Test":"ember-3.2.1-Ember.Test-6a16c3b60e","ember-3.2.1-Ember.ActionSupport":"ember-3.2.1-Ember.ActionSupport-5dcb529b3d","ember-3.2.1-Ember.ClassNamesSupport":"ember-3.2.1-Ember.ClassNamesSupport-f29f5198d1","ember-3.2.1-Ember.TextSupport":"ember-3.2.1-Ember.TextSupport-1bd9a67b28","ember-3.2.1-Ember.ViewMixin":"ember-3.2.1-Ember.ViewMixin-a969d9f653","ember-3.2.1-Ember.EventDispatcher":"ember-3.2.1-Ember.EventDispatcher-db748ebbe8","ember-3.2.1-Ember.CoreView":"ember-3.2.1-Ember.CoreView-6149c3aaea","ember-3.2.1-Ember":"ember-3.2.1-Ember-e49e73cab9","ember-3.2.1-Ember.Templates.helpers":"ember-3.2.1-Ember.Templates.helpers-74bb8edaf8","ember-3.2.1-Function":"ember-3.2.1-Function-2588e72ec2","ember-3.2.1-RSVP":"ember-3.2.1-RSVP-7b07b49340","ember-3.2.1-@ember/application":"ember-3.2.1-@ember/application-cbdc632cb2","ember-3.2.1-@ember/application/deprecations":"ember-3.2.1-@ember/application/deprecations-d0a00fe90b","ember-3.2.1-@ember/array":"ember-3.2.1-@ember/array-13c7a8f487","ember-3.2.1-@ember/component/helper":"ember-3.2.1-@ember/component/helper-c7196da877","ember-3.2.1-@ember/controller":"ember-3.2.1-@ember/controller-6e8202f57f","ember-3.2.1-@ember/debug":"ember-3.2.1-@ember/debug-cd65265639","ember-3.2.1-@ember/engine":"ember-3.2.1-@ember/engine-9f293f475c","ember-3.2.1-@ember/instrumentation":"ember-3.2.1-@ember/instrumentation-9006b2b917","ember-3.2.1-@ember/object":"ember-3.2.1-@ember/object-1b3c78638e","ember-3.2.1-@ember/object/computed":"ember-3.2.1-@ember/object/computed-aae4f94dc7","ember-3.2.1-@ember/object/evented":"ember-3.2.1-@ember/object/evented-e63470d41c","ember-3.2.1-@ember/object/events":"ember-3.2.1-@ember/object/events-bb43b4b351","ember-3.2.1-@ember/object/internals":"ember-3.2.1-@ember/object/internals-543afc4deb","ember-3.2.1-@ember/object/mixin":"ember-3.2.1-@ember/object/mixin-df64531e76","ember-3.2.1-@ember/object/observers":"ember-3.2.1-@ember/object/observers-27aed0ce11","ember-3.2.1-@ember/polyfills":"ember-3.2.1-@ember/polyfills-4b1709fa97","ember-3.2.1-@ember/runloop":"ember-3.2.1-@ember/runloop-acf9626698","ember-3.2.1-@ember/service":"ember-3.2.1-@ember/service-022445cf2e","ember-3.2.1-@ember/string":"ember-3.2.1-@ember/string-69d3471cc7","ember-3.2.1-@ember/template":"ember-3.2.1-@ember/template-1d9962cb6b","ember-3.2.1-@ember/test":"ember-3.2.1-@ember/test-8df2aec123","ember-3.2.1-@ember/utils":"ember-3.2.1-@ember/utils-e4a6b166b4"},"namespace":{"ember-3.2.1-Ember.FEATURES":"ember-3.2.1-Ember.FEATURES-d9a62dd034","ember-3.2.1-Instrumentation":"ember-3.2.1-Instrumentation-6b32653ce6","ember-3.2.1-AutoLocation":"ember-3.2.1-AutoLocation-cb3b8abff2","ember-3.2.1-Ember.inject":"ember-3.2.1-Ember.inject-886621e5c6"},"module":{"ember-3.2.1-@ember/application":"ember-3.2.1-@ember/application-a9a4c5c5b8","ember-3.2.1-@ember/engine":"ember-3.2.1-@ember/engine-9db553e934","ember-3.2.1-@ember/debug":"ember-3.2.1-@ember/debug-88a74415ee","ember-3.2.1-@ember/error":"ember-3.2.1-@ember/error-2c4672b18d","ember-3.2.1-ember":"ember-3.2.1-ember-7d51a3242a","ember-3.2.1-@ember/component":"ember-3.2.1-@ember/component-1392fe0727","ember-3.2.1-@ember/routing":"ember-3.2.1-@ember/routing-c2c06f8e08","ember-3.2.1-@ember/string":"ember-3.2.1-@ember/string-f14e0f1b57","ember-3.2.1-@ember/object":"ember-3.2.1-@ember/object-346b29af9d","ember-3.2.1-@ember/instrumentation":"ember-3.2.1-@ember/instrumentation-6f117937c7","ember-3.2.1-@ember/utils":"ember-3.2.1-@ember/utils-3f4b00dc00","ember-3.2.1-@ember/map":"ember-3.2.1-@ember/map-23665cb33e","ember-3.2.1-@ember/polyfills":"ember-3.2.1-@ember/polyfills-fd53bd8a6d","ember-3.2.1-@ember/runloop":"ember-3.2.1-@ember/runloop-bfbba1c09e","ember-3.2.1-@ember/controller":"ember-3.2.1-@ember/controller-d58fb01a93","ember-3.2.1-@ember/array":"ember-3.2.1-@ember/array-c88c83a535","ember-3.2.1-@ember/service":"ember-3.2.1-@ember/service-512b1916cf","ember-3.2.1-@ember/test":"ember-3.2.1-@ember/test-9925371401"},"missing":{"Ember.Object":"Ember.Object-9c32970d20","Error":"Error-158974c414","Map":"Map-099e18add8"}}}